[{"date":1697616000,"icon":"🌦","temp":300.82,"min":300.25,"max":301.21,"feelsLike":304.05,"pressure":1014,"humidity":77,"windSpeed":6.27,"windDirection":118,"clouds":97,"windGust":7.13,"sunrise":1697595493,"sunset":1697639110},{"date":1697702400,"icon":"🌤","temp":301.46,"min":300.86,"max":301.71,"feelsLike":305.53,"pressure":1013,"humidity":77,"windSpeed":6.48,"windDirection":117,"clouds":19,"windGust":7.13,"sunrise":1697681881,"sunset":1697725499},{"date":1697788800,"icon":"🌦","temp":300.84,"min":300.55,"max":301.18,"feelsLike":304.09,"pressure":1012,"humidity":77,"windSpeed":5.59,"windDirection":129,"clouds":92,"windGust":5.83,"sunrise":1697768269,"sunset":1697811888},{"date":1697875200,"icon":"🌦","temp":300.56,"min":300.36,"max":300.69,"feelsLike":303.48,"pressure":1011,"humidity":77,"windSpeed":3.99,"windDirection":167,"clouds":69,"windGust":4.03,"sunrise":1697854659,"sunset":1697898279},{"date":1697961600,"icon":"🌦","temp":300.86,"min":300.33,"max":300.95,"feelsLike":303.38,"pressure":1011,"humidity":71,"windSpeed":4.37,"windDirection":157,"clouds":8,"windGust":4.6,"sunrise":1697941049,"sunset":1697984670},{"date":1698048000,"icon":"🌦","temp":301.05,"min":300.5,"max":301.28,"feelsLike":304.43,"pressure":1011,"humidity":76,"windSpeed":4.28,"windDirection":127,"clouds":83,"windGust":4.44,"sunrise":1698027440,"sunset":1698071062},{"date":1698134400,"icon":"🌦","temp":301.36,"min":300.69,"max":301.55,"feelsLike":304.97,"pressure":1011,"humidity":75,"windSpeed":5.41,"windDirection":99,"clouds":26,"windGust":6.12,"sunrise":1698113831,"sunset":1698157454},{"date":1698220800,"icon":"🌦","temp":301.54,"min":301.11,"max":301.61,"feelsLike":306.07,"pressure":1011,"humidity":79,"windSpeed":6.43,"windDirection":89,"clouds":100,"windGust":7.38,"sunrise":1698200224,"sunset":1698243848},{"date":1698307200,"icon":"🌦","temp":301.55,"min":300.84,"max":301.55,"feelsLike":305.41,"pressure":1010,"humidity":75,"windSpeed":6.11,"windDirection":101,"clouds":69,"windGust":6.81,"sunrise":1698286617,"sunset":1698330242},{"date":1698393600,"icon":"🌦","temp":301.43,"min":300.95,"max":301.55,"feelsLike":305.46,"pressure":1010,"humidity":77,"windSpeed":5.2,"windDirection":81,"clouds":25,"windGust":5.74,"sunrise":1698373010,"sunset":1698416636},{"date":1698480000,"icon":"🌦","temp":301.02,"min":300.7,"max":301.08,"feelsLike":304.22,"pressure":1010,"humidity":75,"windSpeed":3.62,"windDirection":94,"clouds":7,"windGust":3.9,"sunrise":1698459405,"sunset":1698503032},{"date":1698566400,"icon":"🌦","temp":301.1,"min":300.31,"max":301.27,"feelsLike":304.4,"pressure":1011,"humidity":75,"windSpeed":3.53,"windDirection":132,"clouds":11,"windGust":3.71,"sunrise":1698545801,"sunset":1698589429},{"date":1698652800,"icon":"🌦","temp":301.12,"min":300.44,"max":301.34,"feelsLike":304.16,"pressure":1011,"humidity":73,"windSpeed":4.02,"windDirection":136,"clouds":15,"windGust":4.44,"sunrise":1698632197,"sunset":1698675826},{"date":1698739200,"icon":"🌦","temp":300.93,"min":300.57,"max":301.3,"feelsLike":304.16,"pressure":1011,"humidity":76,"windSpeed":4.65,"windDirection":81,"clouds":49,"windGust":5.03,"sunrise":1698718594,"sunset":1698762224},{"date":1698825600,"icon":"🌦","temp":301.07,"min":300.58,"max":301.22,"feelsLike":304.19,"pressure":1010,"humidity":74,"windSpeed":4.63,"windDirection":91,"clouds":13,"windGust":5.13,"sunrise":1698804992,"sunset":1698848623},{"date":1698912000,"icon":"🌦","temp":301.13,"min":300.46,"max":301.25,"feelsLike":304.32,"pressure":1010,"humidity":74,"windSpeed":4.2,"windDirection":74,"clouds":14,"windGust":4.56,"sunrise":1698891390,"sunset":1698935023}]