[{"date":1723449600,"icon":"🌦","temp":299.32,"min":298.8,"max":299.44,"feelsLike":299.32,"pressure":1012,"humidity":82,"windSpeed":8.13,"windDirection":203,"clouds":71,"windGust":9.5,"sunrise":1723430306,"sunset":1723473897},{"date":1723536000,"icon":"🌦","temp":299.21,"min":298.78,"max":299.21,"feelsLike":299.21,"pressure":1012,"humidity":85,"windSpeed":7.99,"windDirection":165,"clouds":42,"windGust":9.73,"sunrise":1723516696,"sunset":1723560287},{"date":1723622400,"icon":"🌦","temp":299.1,"min":298.88,"max":299.25,"feelsLike":299.1,"pressure":1013,"humidity":82,"windSpeed":8.02,"windDirection":177,"clouds":82,"windGust":9.31,"sunrise":1723603086,"sunset":1723646677},{"date":1723708800,"icon":"🌦","temp":298.92,"min":298.8,"max":299,"feelsLike":299.69,"pressure":1012,"humidity":82,"windSpeed":8.15,"windDirection":191,"clouds":65,"windGust":9.18,"sunrise":1723689475,"sunset":1723733066},{"date":1723795200,"icon":"🌦","temp":298.98,"min":298.79,"max":298.98,"feelsLike":299.76,"pressure":1011,"humidity":82,"windSpeed":8.38,"windDirection":197,"clouds":100,"windGust":9.6,"sunrise":1723775863,"sunset":1723819454},{"date":1723881600,"icon":"🌦","temp":299.01,"min":298.81,"max":299.1,"feelsLike":299.69,"pressure":1011,"humidity":78,"windSpeed":8.83,"windDirection":191,"clouds":97,"windGust":9.88,"sunrise":1723862251,"sunset":1723905842},{"date":1723968000,"icon":"🌦","temp":298.8,"min":298.66,"max":298.96,"feelsLike":299.43,"pressure":1011,"humidity":77,"windSpeed":8.84,"windDirection":183,"clouds":3,"windGust":9.73,"sunrise":1723948639,"sunset":1723992229},{"date":1724054400,"icon":"🌦","temp":298.75,"min":298.39,"max":298.91,"feelsLike":299.43,"pressure":1012,"humidity":79,"windSpeed":8.38,"windDirection":208,"clouds":93,"windGust":9.56,"sunrise":1724035025,"sunset":1724078616},{"date":1724140800,"icon":"🌦","temp":298.96,"min":298.77,"max":298.96,"feelsLike":299.71,"pressure":1011,"humidity":81,"windSpeed":9.69,"windDirection":189,"clouds":94,"windGust":11.31,"sunrise":1724121412,"sunset":1724165003},{"date":1724227200,"icon":"🌦","temp":298.83,"min":298.7,"max":298.88,"feelsLike":299.49,"pressure":1011,"humidity":78,"windSpeed":10.32,"windDirection":185,"clouds":67,"windGust":12.5,"sunrise":1724207798,"sunset":1724251388},{"date":1724313600,"icon":"🌦","temp":298.94,"min":298.66,"max":298.99,"feelsLike":299.56,"pressure":1012,"humidity":76,"windSpeed":8.71,"windDirection":189,"clouds":70,"windGust":10.18,"sunrise":1724294183,"sunset":1724337774},{"date":1724400000,"icon":"🌦","temp":298.95,"min":298.54,"max":298.95,"feelsLike":299.73,"pressure":1011,"humidity":82,"windSpeed":8.75,"windDirection":233,"clouds":95,"windGust":10.36,"sunrise":1724380568,"sunset":1724424158},{"date":1724486400,"icon":"🌦","temp":299.31,"min":298.77,"max":299.31,"feelsLike":299.31,"pressure":1011,"humidity":84,"windSpeed":8.66,"windDirection":228,"clouds":35,"windGust":10.13,"sunrise":1724466952,"sunset":1724510543},{"date":1724572800,"icon":"🌦","temp":299.3,"min":298.92,"max":300.02,"feelsLike":299.3,"pressure":1010,"humidity":84,"windSpeed":6.6,"windDirection":212,"clouds":78,"windGust":7.78,"sunrise":1724553336,"sunset":1724596927},{"date":1724659200,"icon":"🌦","temp":299.51,"min":299.16,"max":299.61,"feelsLike":299.51,"pressure":1011,"humidity":85,"windSpeed":6.63,"windDirection":146,"clouds":78,"windGust":8.27,"sunrise":1724639719,"sunset":1724683310},{"date":1724745600,"icon":"🌦","temp":299.43,"min":299.1,"max":299.58,"feelsLike":299.43,"pressure":1011,"humidity":85,"windSpeed":6.3,"windDirection":169,"clouds":62,"windGust":7.71,"sunrise":1724726102,"sunset":1724769693}]